<flows>
  <!-- BEGIN Common framework flow's -->
  <flow name='devHome' template='main/Dev/devHome' commonWidget='users/siegerstein/common'>
    <widgets>
      <widget id='header'>main/DevPages/home/header</widget>
      <widget id='links'>main/DevPages/home/menu</widget>
      <widget id='footer'>main/DevPages/footer</widget>
    </widgets>
  </flow>
  
  <flow name='WidgetTestPage' template='main/Dev/TestTemplates/Widget'>
    <widgets>
      <widget id='menu'>main/DevPages/TestPages/Widget/menu</widget>
    </widgets>
  </flow>
  
  <flow name='FlowCreationPage' template='main/Dev/TestTemplates/FlowCreation'>
    <widgets>
      <widget id='menu'>main/DevPages/TestPages/FlowCreation/menu</widget>
    </widgets>
  </flow>
  <!-- END Common framework flow's -->
  
  <flow name='flow_1' template='users/siegerstein/mainSite' commonWidget='users/siegerstein/common'>
    <widgets>
      <widget id='logo'>users/siegerstein/logo</widget>
      <widget id='topMenu'>users/siegerstein/topMenu</widget>
      <!-- <widget id='menu'>users/siegerstein/menu</widget> -->
      <widget id='content'>users/siegerstein/content</widget>
      <!-- <widget id='bottom'>users/siegerstein/bottom</widget> -->
    </widgets>
  </flow>
</flows>
